{"chunk_definitions":[{"row":84,"row_count":1,"visible":true,"expansion_state":0,"options":{"engine":"r","label":"setup","include":false},"document_id":"DEA141C4","chunk_id":"csetup_chunk","chunk_label":"setup"},{"row":172,"row_count":1,"visible":true,"expansion_state":0,"options":{"engine":"r","label":"data"},"document_id":"DEA141C4","chunk_id":"ca8wi0j5r9rix","chunk_label":"data"},{"row":362,"row_count":1,"visible":true,"expansion_state":0,"options":{"engine":"r","fig.height":10,"fig.width":8,"fig.align":"centre","label":"unnamed-chunk-17"},"document_id":"DEA141C4","chunk_id":"c027hy69izni5","chunk_label":"unnamed-chunk-2"},{"row":559,"row_count":1,"visible":true,"expansion_state":0,"options":{"engine":"r","fig.width":45,"fig.height":1,"fig.retina":2,"label":"unnamed-chunk-25"},"document_id":"DEA141C4","chunk_id":"cpq9lk9lk3tsd","chunk_label":"unnamed-chunk-5"}],"doc_write_time":1695893440}